jaxprop/__init__.py
jaxprop/bicubic/__init__.py
jaxprop/bicubic/bicubic_interpolation.py
jaxprop/components/__init__.py
jaxprop/components/nozzle_model_core.py
jaxprop/components/nozzle_model_solver.py
jaxprop/coolprop/__init__.py
jaxprop/coolprop/core_calculations.py
jaxprop/coolprop/fluid_properties.py
jaxprop/coolprop/jax_wrapper.py
jaxprop/graphics.py
jaxprop/helpers_jax.py
jaxprop/helpers_props.py
jaxprop/math.py
jaxprop/perfect_gas/__init__.py
jaxprop/perfect_gas/perfect_gas.py
jaxprop/utils.py
jaxprop-0.4.1.dist-info/LICENSE.md
jaxprop-0.4.1.dist-info/METADATA
jaxprop-0.4.1.dist-info/WHEEL
jaxprop-0.4.1.dist-info/RECORD
