Metadata-Version: 2.1
Name: jaxprop
Version: 0.4.1
Summary: JAX-compatible thermodynamic property calculations.
Home-page: https://github.com/turbo-sim/jaxprop
License: MIT
Author: Roberto Agromayor
Requires-Python: >=3.11,<3.14
Classifier: License :: OSI Approved :: MIT License
Classifier: Programming Language :: Python :: 3
Classifier: Programming Language :: Python :: 3.11
Classifier: Programming Language :: Python :: 3.12
Requires-Dist: CoolProp (>=7.0.0,<8.0.0)
Requires-Dist: diffrax (>=0.7.0,<0.8.0)
Requires-Dist: equinox (>=0.12.0,<0.13.0)
Requires-Dist: jax (>=0.6.0,<0.7.0)
Requires-Dist: jaxlib (>=0.6.0,<0.7.0)
Requires-Dist: matplotlib (>=3.10.6,<4.0.0)
Requires-Dist: numpy (>=2.3.0,<3.0.0)
Requires-Dist: optimistix (>=0.0.10,<0.0.11)
Requires-Dist: pysolver_view (>=0.6.8,<0.7.0)
Requires-Dist: scipy (>=1.16.1,<2.0.0)
Requires-Dist: tqdm (>=4.67.1,<5.0.0)
Project-URL: Documentation, https://github.com/turbo-sim/jaxpconrop
Project-URL: Repository, https://github.com/turbo-sim/jaxprop
